wscheck/__init__.py
wscheck/__main__.py
wscheck/checker.py
wscheck/printer.py
wscheck/version.py
wscheck-1.3.2.dist-info/LICENSE
wscheck-1.3.2.dist-info/METADATA
wscheck-1.3.2.dist-info/WHEEL
wscheck-1.3.2.dist-info/entry_points.txt
wscheck-1.3.2.dist-info/top_level.txt
wscheck-1.3.2.dist-info/RECORD
