Metadata-Version: 2.1
Name: wscheck
Version: 1.3.2
Summary: Whitespace checking tool
Home-page: https://github.com/andras-tim/wscheck
Author: Andras Tim
Author-email: andras.tim@gmail.com
License: GPLv3
Keywords: whitespace ws check
Platform: any
Classifier: Development Status :: 5 - Production/Stable
Classifier: Intended Audience :: Developers
Classifier: License :: OSI Approved :: GNU General Public License v3 (GPLv3)
Classifier: Programming Language :: Python :: 2
Requires-Dist: lxml (>=2.3)
Requires-Dist: termcolor (<1.2,>=1.1.0)
